{"lab": {"id":  "VLS10",
                    "name": "software engineering lab",
                    "discipline_id": "cse",
                    "institute_id": "iitkgp",
                    "developers": [{"name":"dev1", "email": "dev1_id"},
                    {"name":"dev2", "email": "dev2_id"}],
                    "hosting_info": [{"hosting_status": "hosted", "hosted_on": "institute", "hosted_url": "http://vlabs.iitkgp.ernet.in/se/"}],
                    "integration_level": "4",
                    "assets": [{"asset_type": "image", "path": "vlabs.ac.in/images/static/logo.png"},
                                {"asset_type": "video", "path": "vlabs.ac.in/video/abc.mkv"}],
                    "overview": "This lab deals with software engineering lab" , 
                    "experiments" : ["e99159", 
 							 "e99158", 
 							 "e99157", 
 							 "e99156", 
 							 "e99155", 
 							 "e99154", 
 							 "e99153", 
 							 "e99152", 
 							 "e99151", 
 							 "e99150"]
                  }
}
