{"experiment": {"id":  "e99876",
	 	"name": "Thread Rolling",
	 	"discipline_id": "mech",
	        "institute_id": "dei",
	        "developers": [],
	        "hosting_info": [{"hosting_status": "hosted", "hosted_on": "cloud", "hosted_url": "http://msvs-dei.vlabs.ac.in"},
			 {"hosting_status": "hosted", "hosted_on": "openedx", "hosted_url": "http://msvs-dei.vlabs.ac.in"}],
	        "integration_level": 6,
	        "assets": [{"asset_type": "image", "path": "https://github.com/Virtual-Labs/metal-forming-virtual-simulation-lab-dei"},
	 		   {"asset_type": "video", "path": "https://github.com/Virtual-Labs/metal-forming-virtual-simulation-lab-dei"}],
	 	"overview": "This experiments deals with Thread Rolling",
	 	"sections" : [" Thread Rolling ", 
 			      "Thread Rolling using flat dies ", 
 			      "Thread Rolling using set of two rolls ", 
 			      "Thread Rolling using set of three rolls ", 
 			      "SELF CHECK QUIZ - THREAD ROLLING "]		
		}
}