{"experiment": {"id":  "e99547",
	 	"name": "Binary vapor liquid equilibrium",
	 	"discipline_id": "chem-engg",
	        "institute_id": "iitg",
	        "developers": [],
	        "hosting_info": [{"hosting_status": "hosted", "hosted_on": "cloud", "hosted_url": "http://vmt-iitg.vlabs.ac.in"},
			 {"hosting_status": "hosted", "hosted_on": "openedx", "hosted_url": "http://vmt-iitg.vlabs.ac.in"}],
	        "integration_level": 6,
	        "assets": [{"asset_type": "image", "path": "https://github.com/Virtual-Labs/virtual-mass-transfer-lab-iitg"},
	 		   {"asset_type": "video", "path": "https://github.com/Virtual-Labs/virtual-mass-transfer-lab-iitg"}],
	 	"overview": "This experiments deals with Binary vapor liquid equilibrium",
	 	"sections" : ["Theory", 
 			      "Procedure", 
 			      "Labview Calc", 
 			      "Pre Quiz", 
 			      "Download", 
 			      "Simulator", 
 			      "Post Expt Quiz", 
 			      "Videos"]		
		}
}