{
    "lab": { 
        "id":  "biotech19",
        "name": "neuron simulation lab (pilot)",
        "discipline_id": "biotech",
        "institute_id": "amrita",
        "developers": [],
        "hosting_info": [
            {
                "hosting_status": "hosted",
                "hosted_on": "institute",
                "hosted_url": "http://vlab.amrita.edu/?sub=3&brch=212"
            }
        ],
        "integration_level": 4,
        "overview": "This lab deals with neuron simulation lab (pilot)",
        "assets": [],
        "sections": [ 
            {
                "name": "Introduction"
            }, 
            {
                "experiments" : [
                    "e98801", 
                    "e98800", 
                    "e98799", 
                    "e98798", 
                    "e98797", 
                    "e98796", 
                    "e98795", 
                    "e98794", 
                    "e98793", 
                    "e98792"
                ]
            }
        ]
    }
}
