{
    "lab": {
        "id":  "ece08",
        "name": "engineering electromagnetic lab",
        "discipline_id": "ece",
        "institute_id": "iitd",
        "developers": [
            {
                "name": "Mahesh P Abegaonkar",
                "email": "mpjosh@care.iitd.ernet.in"
            }
        ],
        "hosting_info": [
            {
                "hosting_status": "hosted",
                "hosted_on": "cloud",
                "hosted_url": "http://vlabs.ac.in/courses/course-v1:IIT-Delhi+ECE08+Anytime/about"
            },
            {
                "hosting_status": "hosted",
                "hosted_on": "openedx",
                "hosted_url": "http://vlabs.ac.in/courses/course-v1:IIT-Delhi+ECE08+Anytime/about"
            }
        ],
        "integration_level": 4,
        "overview": "This lab deals with engineering electromagnetic lab",
        "assets": [
            {
                "asset_type": "sources",
                "path": "https://github.com/Virtual-Labs/engineering-electro-magnetics-laboratory-iitd.git"
            }
        ],
        "sections": [ 
            {
                "name": "Introduction"
            }, 
            {
                "experiments" : [
                    "e98763"
                ]
            }
        ]
    }
}
